<?xml version="1.0" encoding="UTF-8"?>
<objects serializationModel="Studio.02.01.00">
	<object class="AudioFile" id="{f633f02f-853d-409d-bedf-88fa5030a961}">
		<property name="assetPath">
			<value>Bras_G_OneShot.wav</value>
		</property>
		<property name="frequencyInKHz">
			<value>48</value>
		</property>
		<property name="channelCount">
			<value>2</value>
		</property>
		<property name="length">
			<value>0.86310416666666667</value>
		</property>
		<relationship name="masterAssetFolder">
			<destination>{300729fc-c35a-4c8e-a5df-f16355a77db1}</destination>
		</relationship>
	</object>
</objects>
